sandpsue/__init__.py
sandpsue/client/__init__.py
sandpsue/client/client.py
sandpsue/errors/__init__.py
sandpsue/errors/errors.py
sandpsue/server/__init__.py
sandpsue/server/server.py
sandpsue/util/__init__.py
sandpsue/util/util.py
sandpsue-0.2.dist-info/METADATA
sandpsue-0.2.dist-info/WHEEL
sandpsue-0.2.dist-info/top_level.txt
sandpsue-0.2.dist-info/RECORD
