Metadata-Version: 2.1
Name: sandpsue
Version: 0.2
Requires-Dist: numpy
Requires-Dist: pandas
